{
  "targetSite": "koton",
  "urls": [
    "https://www.koton.com/kadin-canta/"
  ],
  "totalUrls": 1,
  "paused": false,
  "pausedReason": "",
  "configurations": [
    {
      "brand": "koton",
      "paginationElement": ".pz-pagination-link",
      "paginationParameter": "?page=",
      "scrollable": true,
      "showMoreButton": ".js-loadmore-products",
      "productCounter": ".js-result-count",
      "urls": [
        "https://www.koton.com/kadin-canta/"
      ],
      "paused": false,
      "pausedReason": "[\".pz-pagination-link\"]",
      "rowIndex": 2
    }
  ],
  "paginationElement": ".pz-pagination-link",
  "paginationParameter": "?page=",
  "scrollable": true,
  "showMoreButton": ".js-loadmore-products",
  "productCounter": ".js-result-count"
}